Metadata-Version: 1.2
Name: MyTact
Version: 1.0.1
Summary: A Simple Contacts App for managing contacts right from the command line
Home-page: https://github.com/CITGuru/MyTact/
Author: Oyetoke Toby
Author-email: oyetoketoby80@gmail.com
License: MIT
Download-URL: https://github.com/CITGuru/MyTact/archive/1.0.0.tar.gz
Platform: UNKNOWN
Requires-Python: >=2.7
